LICENSE
MANIFEST.in
README.rst
setup.cfg
setup.py
dj_ingredient_field/__init__.py
dj_ingredient_field/apps.py
dj_ingredient_field/enums.py
dj_ingredient_field/exceptions.py
dj_ingredient_field/settings.py
dj_ingredient_field/urls.py
dj_ingredient_field/views.py
dj_ingredient_field/widgets.py
dj_ingredient_field/migrations/__init__.py
dj_ingredient_field/static/dj_ingredient_field/js/lazy_dropdown.js
dj_ingredient_field/templates/dj_ingredient_field/lazy_choice.html
dj_ingredient_field/tests/__init__.py
dj_ingredient_field/tests/models.py
dj_ingredient_field/tests/test_fields.py
dj_ingredient_field/tests/test_representations.py
dj_ingredient_field/tests/utils.py
django_ingredient_field.egg-info/PKG-INFO
django_ingredient_field.egg-info/SOURCES.txt
django_ingredient_field.egg-info/dependency_links.txt
django_ingredient_field.egg-info/requires.txt
django_ingredient_field.egg-info/top_level.txt
docs/Makefile
docs/conf.py
docs/dj_ingredient_field.rst
docs/examples.rst
docs/index.rst
docs/make.bat
docs/settings.rst
docs/urls.rst
docs/widgets.rst